AUTHORS
BUGS.md
CHANGES.rst
LICENSE
MANIFEST.in
README.rst
TODO.md
setup.py
docs/Makefile
docs/api.rst
docs/api_benchmark_assess.rst
docs/api_filter_abstract_cleaning_algorithm.rst
docs/api_filter_inverse_transform_sampling.rst
docs/api_filter_rejection_criteria.rst
docs/api_filter_tailcut.rst
docs/api_filter_wavelet_mrfilter.rst
docs/api_filter_wavelet_mrtransform.rst
docs/api_image_hillas_parameters.rst
docs/api_image_signal_to_border_distance.rst
docs/api_io_geometry_converter.rst
docs/api_io_images.rst
docs/api_io_simtel.rst
docs/api_io_simtel_to_fits.rst
docs/api_optimization_bruteforce.rst
docs/api_optimization_differential_evolution.rst
docs/api_optimization_objectivefunc_tailcut.rst
docs/api_optimization_objectivefunc_wavelets_mrfilter.rst
docs/api_optimization_objectivefunc_wavelets_mrtransform.rst
docs/api_optimization_saes.rst
docs/conf.py
docs/developer.rst
docs/index.rst
docs/init_sphinx.sh
docs/intro.rst
docs/logo_asterics.png
docs/logo_cea.png
docs/logo_cta.pdf
docs/logo_irfu.png
docs/logo_univearths.jpeg
docs/make.bat
examples/example_get_number_of_pixels_clusters.py
examples/plot_ctapipe_dataset.py
examples/plot_wavelet_mrtransform.py
pywicta/__init__.py
pywicta.egg-info/PKG-INFO
pywicta.egg-info/SOURCES.txt
pywicta.egg-info/dependency_links.txt
pywicta.egg-info/entry_points.txt
pywicta.egg-info/requires.txt
pywicta.egg-info/top_level.txt
pywicta/benchmark/__init__.py
pywicta/benchmark/assess.py
pywicta/data/__init__.py
pywicta/data/lst_gamma_r104_prod3b-north_t1_e1016403_660GeV.fits
pywicta/data/lst_gamma_r104_prod3b-north_t1_e6905_87GeV.fits
pywicta/data/lst_gamma_r104_prod3b-north_t2_e229401_18GeV.fits
pywicta/data/lst_gamma_r104_prod3b-north_t4_e40200_22GeV.fits
pywicta/data/lst_gamma_prod3b_north_faint/__init__.py
pywicta/data/lst_gamma_prod3b_north_faint/gamma_20deg_0deg_run104___cta-prod3-lapalma3-2147m-LaPalma.simtel.gz_TEL001_EV06905.fits
pywicta/data/lst_gamma_prod3b_north_faint/gamma_20deg_0deg_run104___cta-prod3-lapalma3-2147m-LaPalma.simtel.gz_TEL001_EV100801.fits
pywicta/data/lst_gamma_prod3b_north_faint/gamma_20deg_0deg_run104___cta-prod3-lapalma3-2147m-LaPalma.simtel.gz_TEL001_EV137301.fits
