Metadata-Version: 1.2
Name: pywicta
Version: 0.4.dev3
Summary: PyWI CTA wrapper - a signal processing library for Imaging Atmospheric Cherenkov Telescopes
Home-page: https://github.com/jeremiedecock/pywi-cta
Author: Jeremie DECOCK and Tino Michael
Author-email: jd.jdhp@gmail.com
Maintainer: Jeremie DECOCK and Tino Michael
Maintainer-email: jd.jdhp@gmail.com
License: UNKNOWN
Download-URL: https://github.com/jeremiedecock/pywi-cta
Keywords: wavelet imaging cherenkov telescope array
Platform: UNKNOWN
Classifier: Development Status :: 4 - Beta
Classifier: Intended Audience :: Developers
Classifier: License :: OSI Approved :: MIT License
Classifier: Natural Language :: English
Classifier: Operating System :: OS Independent
Classifier: Programming Language :: Python :: 3
Classifier: Topic :: Software Development :: Libraries
Classifier: Topic :: Software Development :: Libraries :: Python Modules
Classifier: Topic :: Software Development :: Libraries :: Application Frameworks
